arborsort/__init__.py
arborsort/cli.py
arborsort/core.py
arborsort/utils.py
arborsort-0.1.1.dist-info/METADATA
arborsort-0.1.1.dist-info/WHEEL
arborsort-0.1.1.dist-info/entry_points.txt
arborsort-0.1.1.dist-info/top_level.txt
arborsort-0.1.1.dist-info/RECORD
