Metadata-Version: 2.4
Name: arborsort
Version: 0.1.1
Summary: A lightweight CLI tool to classify and organize files into folders based on their file types.
Author-email: Izzoudine KANTA <izzoudine.kanta@epitech.eu>
License: MIT
Requires-Python: >=3.8
